[
  {
    "type": "function",
    "inputs": [
      {
        "name": "_requestId",
        "type": "uint256",
        "baseType": "uint256",
        "components": null,
        "arrayLength": null,
        "arrayChildren": null
      },
      {
        "name": "_price",
        "type": "uint256",
        "baseType": "uint256",
        "components": null,
        "arrayLength": null,
        "arrayChildren": null
      }
    ],
    "name": "dataFeedBack",
    "constant": false,
    "outputs": [],
    "stateMutability": "nonpayable",
    "payable": false,
    "gas": null
  },
  {
    "type": "function",
    "inputs": [],
    "name": "price",
    "constant": true,
    "outputs": [
      {
        "name": "",
        "type": "uint256",
        "baseType": "uint256",
        "components": null,
        "arrayLength": null,
        "arrayChildren": null
      }
    ],
    "stateMutability": "view",
    "payable": false,
    "gas": null
  },
  {
    "type": "function",
    "inputs": [],
    "name": "recentRequestId",
    "constant": true,
    "outputs": [
      {
        "name": "",
        "type": "uint256",
        "baseType": "uint256",
        "components": null,
        "arrayLength": null,
        "arrayChildren": null
      }
    ],
    "stateMutability": "view",
    "payable": false,
    "gas": null
  },
  {
    "type": "function",
    "inputs": [
      {
        "name": "_oracleContractAddr",
        "type": "address",
        "baseType": "address",
        "components": null,
        "arrayLength": null,
        "arrayChildren": null
      },
      {
        "name": "_currencyPair",
        "type": "string",
        "baseType": "string",
        "components": null,
        "arrayLength": null,
        "arrayChildren": null
      }
    ],
    "name": "updatePrice",
    "constant": false,
    "outputs": [],
    "stateMutability": "payable",
    "payable": true,
    "gas": null
  }
]